AWholeS/__init__.py
AWholeS/__main__.py
AWholeS/ec2.py
AWholeS/sts_calls.py
AWholeS/trusted_advisor_security.py
AWholeS-0.0.2.dist-info/LICENSE
AWholeS-0.0.2.dist-info/METADATA
AWholeS-0.0.2.dist-info/WHEEL
AWholeS-0.0.2.dist-info/top_level.txt
AWholeS-0.0.2.dist-info/RECORD
