Metadata-Version: 2.1
Name: AWholeS
Version: 0.0.2
Summary: A project to review the security posture in AWS
Author: w0rmr1d3r
License: MIT
Project-URL: Homepage, https://github.com/w0rmr1d3r/AWholeS
Project-URL: Repository, https://github.com/w0rmr1d3r/AWholeS
Project-URL: Bug Tracker, https://github.com/w0rmr1d3r/AWholeS/issues
Project-URL: Documentation, https://github.com/w0rmr1d3r/AWholeS
Project-URL: Changelog, https://github.com/w0rmr1d3r/AWholeS
Keywords: aws,security,cloudformation,python
Requires-Python: >=3.9
License-File: LICENSE
Requires-Dist: boto3 (>=1.26.26)
Requires-Dist: inquirer (~=3.0)
Provides-Extra: dev
Requires-Dist: black (~=22.0) ; extra == 'dev'
Requires-Dist: pip-tools (~=6.0) ; extra == 'dev'
